md2lobster/__init__.py
md2lobster/md2lobster.py
md2lobster-0.1.0.dist-info/METADATA
md2lobster-0.1.0.dist-info/WHEEL
md2lobster-0.1.0.dist-info/entry_points.txt
md2lobster-0.1.0.dist-info/licenses/LICENSE
md2lobster-0.1.0.dist-info/RECORD
