Metadata-Version: 2.4
Name: md2lobster
Version: 0.1.0
Summary: Read a markdown file to create some lobster traceing
Project-URL: Homepage, https://codeberg.org/balp/md2lobster
Project-URL: Issues, https://codeberg.org/balp/md2lobster/issues
Author-email: Anders Arnholm <Anders@Arnholm.se>
License-Expression: ISC
License-File: LICENSE
Classifier: Operating System :: OS Independent
Classifier: Programming Language :: Python :: 3
Requires-Python: >=3.9
Requires-Dist: markdown-it-py
